zzhprobm/Binomialdistribution.py
zzhprobm/Gaussiandistribution.py
zzhprobm/Generaldistribution.py
zzhprobm/__init__.py
zzhprobm-0.4.dist-info/METADATA
zzhprobm-0.4.dist-info/WHEEL
zzhprobm-0.4.dist-info/top_level.txt
zzhprobm-0.4.dist-info/RECORD
