Metadata-Version: 2.1
Name: zzhprobm
Version: 0.4
Summary: Gaussian distributions
Home-page: UNKNOWN
Author: maxoyed
Author-email: maxoyed@gmail.com
License: UNKNOWN
Platform: any
Requires-Dist: matplotlib (==3.3.2)
